{
  "games": [
	{
		"gameId" : 419,
		"homeTeam" : 1,
		"awayTeam" : 26,
		"favorite" : 1,
		"spread" : 20.5,
		"required" : false,
		"gameTime" : "2020-12-19T17:00Z",
		"channel": "FOX"
	},
	{
		"gameId" : 420,
		"homeTeam" : 23,
		"awayTeam" : 73,
		"favorite" : 73,
		"spread" : 13.5,
		"required" : false,
		"gameTime" : "2020-12-19T17:00Z",
		"channel": "ESPN"
	},
	{
		"gameId" : 421,
		"homeTeam" : 99,
		"awayTeam" : 55,
		"favorite" : 55,
		"spread" : 5.5,
		"required" : false,
		"gameTime" : "2020-12-19T17:00Z",
		"channel": "ABC"
	},
	{
		"gameId" : 422,
		"homeTeam" : 34,
		"awayTeam" : 33,
		"favorite" : 34,
		"spread" : 38.5,
		"required" : false,
		"gameTime" : "2020-12-19T17:00Z",
		"channel": "SECN"
	},
	{
		"gameId" : 423,
		"homeTeam" : 90,
		"awayTeam" : 31,
		"favorite" : 90,
		"spread" : 6.5,
		"required" : false,
		"gameTime" : "2020-12-19T17:00Z",
		"channel": "ACCN"
	},
	{
		"gameId" : 424,
		"homeTeam" : 78,
		"awayTeam" : 49,
		"favorite" : 78,
		"spread" : 10.5,
		"required" : false,
		"gameTime" : "2020-12-19T18:30Z",
		"channel": "FS1"
	},
	{
		"gameId" : 425,
		"homeTeam" : 82,
		"awayTeam" : 106,
		"favorite" : 106,
		"spread" : 2.5,
		"required" : false,
		"gameTime" : "2020-12-19T20:00Z",
		"channel": "CBSSN"
	},
	{
		"gameId" : 426,
		"homeTeam" : 19,
		"awayTeam" : 14,
		"favorite" : 19,
		"spread" : 3.5,
		"required" : false,
		"gameTime" : "2020-12-19T20:30Z",
		"channel": "ESPN"
	},
	{
		"gameId" : 427,
		"homeTeam" : 13,
		"awayTeam" : 44,
		"favorite" : 44,
		"spread" : 1.5,
		"required" : false,
		"gameTime" : "2020-12-19T20:30Z",
		"channel": "SECN ALT"
	},
	{
		"gameId" : 428,
		"homeTeam" : 35,
		"awayTeam" : 12,
		"favorite" : 35,
		"spread" : 1.5,
		"required" : false,
		"gameTime" : "2020-12-19T20:30Z",
		"channel": "SECN"
	},
	{
		"gameId" : 429,
		"homeTeam" : 129,
		"awayTeam" : 57,
		"favorite" : 57,
		"spread" : 10.5,
		"required" : true,
		"gameTime" : "2020-12-19T21:00Z",
		"channel": "ABC"
	},
	{
		"gameId" : 430,
		"homeTeam" : 83,
		"awayTeam" : 74,
		"favorite" : 83,
		"spread" : 10.5,
		"required" : false,
		"gameTime" : "2020-12-19T21:00Z",
		"channel": "BTN"
	},
	{
		"gameId" : 431,
		"homeTeam" : 75,
		"awayTeam" : 32,
		"favorite" : 32,
		"spread" : 6.5,
		"required" : false,
		"gameTime" : "2020-12-19T21:15Z",
		"channel": "FOX"
	},
	{
		"gameId" : 432,
		"homeTeam" : 112,
		"awayTeam" : 30,
		"favorite" : 30,
		"spread" : 7.5,
		"required" : false,
		"gameTime" : "2020-12-20T21:30Z",
		"channel": "ESPN2"
	},
	{
		"gameId" : 433,
		"homeTeam" : 105,
		"awayTeam" : 5,
		"favorite" : 105,
		"spread" : 14.5,
		"required" : false,
		"gameTime" : "2020-12-19T22:30Z",
		"channel": "FS1"
	},
	{
		"gameId" : 434,
		"homeTeam" : 41,
		"awayTeam" : 37,
		"favorite" : 41,
		"spread" : 13.5,
		"required" : false,
		"gameTime" : "2020-12-20T00:00Z",
		"channel": "ESPN"
	},
	{
		"gameId" : 435,
		"homeTeam" : 97,
		"awayTeam" : 86,
		"favorite" : 97,
		"spread" : 1.5,
		"required" : false,
		"gameTime" : "2020-12-20T00:30Z",
		"channel": "BTN"
	},
	{
		"gameId" : 436,
		"homeTeam" : 53,
		"awayTeam" : 17,
		"favorite" : 17,
		"spread" : 17.5,
		"required" : false,
		"gameTime" : "2020-12-20T01:00Z",
		"channel": "CBS"
	},
	{
		"gameId" : 437,
		"homeTeam" : 62,
		"awayTeam" : 85,
		"favorite" : 62,
		"spread" : 15.5,
		"required" : false,
		"gameTime" : "2020-12-20T01:00Z",
		"channel": "ABC"
	},
	{
		"gameId" : 438,
		"homeTeam" : 61,
		"awayTeam" : 25,
		"favorite" : 61,
		"spread" : 7.5,
		"required" : false,
		"gameTime" : "2020-12-20T01:00Z",
		"channel": "ESPN2"
	},
	{
		"gameId" : 439,
		"homeTeam" : 94,
		"awayTeam" : 40,
		"favorite" : 40,
		"spread" : 8.5,
		"required" : false,
		"gameTime" : "2020-12-20T02:00Z",
		"channel": "FS1"
	},
	{
		"gameId" : 440,
		"homeTeam" : 96,
		"awayTeam" : 76,
		"favorite" : 76,
		"spread" : 7.5,
		"required" : false,
		"gameTime" : "2020-12-20T03:3Z",
		"channel": "ESPN"
	}
  ]
}