{
  "games": [
    {
		"gameId" : 182,
		"awayTeam" : "PUR",
		"homeTeam" : "MINN",
		"favorite" : "MINN",
		"spread" : 12.5,
		"required" : false,
		"gameTime" : "2022-10-01T16:00:00Z",
		"channel": "ESPN2"
    },
    {
		"gameId" : 183,
		"awayTeam" : "GSU",
		"homeTeam" : "ARMY",
		"favorite" : "ARMY",
		"spread" : 7.5,
		"required" : false,
		"gameTime" : "2022-10-01T16:00:00Z",
		"channel": "CBSSN"
    },
    {
		"gameId" : 184,
		"awayTeam" : "NAVY",
		"homeTeam" : "AFA",
		"favorite" : "AFA",
		"spread" : 14.5,
		"required" : false,
		"gameTime" : "2022-10-01T16:00:00Z",
		"channel": "CBS"
    },
    {
		"gameId" : 185,
		"awayTeam" : "LOU",
		"homeTeam" : "BC",
		"favorite" : "LOU",
		"spread" : 15.5,
		"required" : false,
		"gameTime" : "2022-10-01T16:00:00Z",
		"channel": "ACCN"
    },
    {
		"gameId" : 186,
		"awayTeam" : "ILL",
		"homeTeam" : "WIS",
		"favorite" : "WIS",
		"spread" : 7.5,
		"required" : false,
		"gameTime" : "2022-10-01T16:00:00Z",
		"channel": "B1G"
    },
    {
		"gameId" : 187,
		"awayTeam" : "TEMPLE",
		"homeTeam" : "MEM",
		"favorite" : "MEM",
		"spread" : 18.5,
		"required" : false,
		"gameTime" : "2022-10-01T16:00:00Z",
		"channel": "ESPNU"
    },
    {
		"gameId" : 188,
		"awayTeam" : "MICH",
		"homeTeam" : "IOWA",
		"favorite" : "MICH",
		"spread" : 10.5,
		"required" : false,
		"gameTime" : "2022-10-01T16:00:00Z",
		"channel": "FOX"
    },
    {
		"gameId" : 189,
		"awayTeam" : "OU",
		"homeTeam" : "TCU",
		"favorite" : "OU",
		"spread" : 6.5,
		"required" : false,
		"gameTime" : "2022-10-01T16:00:00Z",
		"channel": "ABC"
    },
    {
		"gameId" : 190,
		"awayTeam" : "TEXTCH",
		"homeTeam" : "K-STATE",
		"favorite" : "K-STATE",
		"spread" : 8.5,
		"required" : false,
		"gameTime" : "2022-10-01T16:00:00Z",
		"channel": "ESPN+"
    },
    {
		"gameId" : 191,
		"awayTeam" : "UK",
		"homeTeam" : "MISS",
		"favorite" : "MISS",
		"spread" : 7.5,
		"required" : false,
		"gameTime" : "2022-10-01T16:00:00Z",
		"channel": "ESPN"
    },
    {
		"gameId" : 192,
		"awayTeam" : "TEXST",
		"homeTeam" : "JMU",
		"favorite" : "JMU",
		"spread" : 22.5,
		"required" : false,
		"gameTime" : "2022-10-01T17:30:00Z",
		"channel": "ESPN+"
    },
    {
		"gameId" : 193,
		"awayTeam" : "NIU",
		"homeTeam" : "BALLST",
		"favorite" : "NIU",
		"spread" : 3.5,
		"required" : false,
		"gameTime" : "2022-10-01T18:00:00Z",
		"channel": "ESPN+"
    },
    {
		"gameId" : 194,
		"awayTeam" : "OREST",
		"homeTeam" : "UTAH",
		"favorite" : "UTAH",
		"spread" : 10.5,
		"required" : false,
		"gameTime" : "2022-10-01T18:00:00Z",
		"channel": "PACN"
    },
    {
		"gameId" : 195,
		"awayTeam" : "UMASS",
		"homeTeam" : "EMU",
		"favorite" : "EMU",
		"spread" : 19.5,
		"required" : false,
		"gameTime" : "2022-10-01T18:00:00Z",
		"channel": "ESPN+"
    },
    {
		"gameId" : 196,
		"awayTeam" : "ECU",
		"homeTeam" : "USF",
		"favorite" : "ECU",
		"spread" : 9.5,
		"required" : false,
		"gameTime" : "2022-10-01T18:30:00Z",
		"channel": "ESPN+"
    },
    {
		"gameId" : 197,
		"awayTeam" : "WAKE",
		"homeTeam" : "FSU",
		"favorite" : "FSU",
		"spread" : 6.5,
		"required" : false,
		"gameTime" : "2022-10-01T19:30:00Z",
		"channel": "ABC"
    },
    {
		"gameId" : 198,
		"awayTeam" : "NU",
		"homeTeam" : "PSU",
		"favorite" : "PSU",
		"spread" : 25.5,
		"required" : false,
		"gameTime" : "2022-10-01T19:30:00Z",
		"channel": "ESPN"
    },
    {
		"gameId" : 199,
		"awayTeam" : "VT",
		"homeTeam" : "UNC",
		"favorite" : "UNC",
		"spread" : 8.5,
		"required" : false,
		"gameTime" : "2022-10-01T19:30:00Z",
		"channel": "ACCN"
    },
    {
		"gameId" : 200,
		"awayTeam" : "OKST",
		"homeTeam" : "BAYLOR",
		"favorite" : "BAYLOR",
		"spread" : 2.5,
		"required" : false,
		"gameTime" : "2022-10-01T19:30:00Z",
		"channel": "FOX"
    },
    {
		"gameId" : 201,
		"awayTeam" : "IOWAST",
		"homeTeam" : "KAN",
		"favorite" : "IOWAST",
		"spread" : 3.5,
		"required" : false,
		"gameTime" : "2022-10-01T19:30:00Z",
		"channel": "ESPN2"
    },
    {
		"gameId" : 202,
		"awayTeam" : "MSU",
		"homeTeam" : "MD",
		"favorite" : "MD",
		"spread" : 8.5,
		"required" : false,
		"gameTime" : "2022-10-01T19:30:00Z",
		"channel": "FS1"
    },
    {
		"gameId" : 203,
		"awayTeam" : "ALA",
		"homeTeam" : "ARK",
		"favorite" : "ALA",
		"spread" : 17.5,
		"required" : false,
		"gameTime" : "2022-10-01T19:30:00Z",
		"channel": "CBS"
    },
    {
		"gameId" : 204,
		"awayTeam" : "FRESNST",
		"homeTeam" : "UCONN",
		"favorite" : "FRESNST",
		"spread" : 24.5,
		"required" : false,
		"gameTime" : "2022-10-01T19:30:00Z",
		"channel": "CBSSN"
    },
    {
		"gameId" : 205,
		"awayTeam" : "MIA-OH",
		"homeTeam" : "BUFF",
		"favorite" : "BUFF",
		"spread" : 1.5,
		"required" : false,
		"gameTime" : "2022-10-01T19:30:00Z",
		"channel": "ESPNU"
    },
    {
		"gameId" : 206,
		"awayTeam" : "RUTG",
		"homeTeam" : "OSU",
		"favorite" : "OSU",
		"spread" : 40.5,
		"required" : false,
		"gameTime" : "2022-10-01T19:30:00Z",
		"channel": "B1G"
    },
    {
		"gameId" : 207,
		"awayTeam" : "BGSU",
		"homeTeam" : "AKRON",
		"favorite" : "BGSU",
		"spread" : 9.5,
		"required" : false,
		"gameTime" : "2022-10-01T19:30:00Z",
		"channel": "ESPN+"
    },
    {
		"gameId" : 208,
		"awayTeam" : "CMICH",
		"homeTeam" : "TOLEDO",
		"favorite" : "TOLEDO",
		"spread" : 7.5,
		"required" : false,
		"gameTime" : "2022-10-01T19:30:00Z",
		"channel": "NFLN"
    },
    {
		"gameId" : 209,
		"awayTeam" : "OHIO",
		"homeTeam" : "KENT",
		"favorite" : "KENT",
		"spread" : 11.5,
		"required" : false,
		"gameTime" : "2022-10-01T19:30:00Z",
		"channel": "ESPN+"
    },
    {
		"gameId" : 210,
		"awayTeam" : "TXA&M",
		"homeTeam" : "MSST",
		"favorite" : "MSST",
		"spread" : 3.5,
		"required" : false,
		"gameTime" : "2022-10-01T20:00:00Z",
		"channel": "SECN"
    },
    {
		"gameId" : 211,
		"awayTeam" : "GEOSOU",
		"homeTeam" : "COCAR",
		"favorite" : "COCAR",
		"spread" : 10.5,
		"required" : false,
		"gameTime" : "2022-10-01T20:00:00Z",
		"channel": "ESPN+"
    },
    {
		"gameId" : 212,
		"awayTeam" : "FAU",
		"homeTeam" : "UNT",
		"favorite" : "FAU",
		"spread" : 3.5,
		"required" : false,
		"gameTime" : "2022-10-01T20:00:00Z",
		"channel": "ESPN+"
    },
    {
		"gameId" : 213,
		"awayTeam" : "SOALA",
		"homeTeam" : "LA",
		"favorite" : "SOALA",
		"spread" : 8.5,
		"required" : false,
		"gameTime" : "2022-10-01T21:00:00Z",
		"channel": "ESPN+"
    },
    {
		"gameId" : 214,
		"awayTeam" : "CAL",
		"homeTeam" : "WSU",
		"favorite" : "WSU",
		"spread" : 3.5,
		"required" : false,
		"gameTime" : "2022-10-01T21:30:00Z",
		"channel": "PACN"
    },
    {
		"gameId" : 215,
		"awayTeam" : "LIB",
		"homeTeam" : "ODU",
		"favorite" : "LIB",
		"spread" : 3.5,
		"required" : false,
		"gameTime" : "2022-10-01T21:00:00Z",
		"channel": "ESPN+"
    },
    {
		"gameId" : 216,
		"awayTeam" : "UTEP",
		"homeTeam" : "CHAR",
		"favorite" : "UTEP",
		"spread" : 2.5,
		"required" : false,
		"gameTime" : "2022-10-01T22:00:00Z",
		"channel": "ESPN3"
    },
    {
		"gameId" : 217,
		"awayTeam" : "LSU",
		"homeTeam" : "AUB",
		"favorite" : "LSU",
		"spread" : 8.5,
		"required" : false,
		"gameTime" : "2022-10-01T23:00:00Z",
		"channel": "ESPN"
    },
    {
		"gameId" : 218,
		"awayTeam" : "LAMON",
		"homeTeam" : "ARKST",
		"favorite" : "ARKST",
		"spread" : 7.5,
		"required" : false,
		"gameTime" : "2022-10-01T20:00:00Z",
		"channel": "ESPN+"
    },
    {
		"gameId" : 219,
		"awayTeam" : "CIN",
		"homeTeam" : "TULSA",
		"favorite" : "CIN",
		"spread" : 9.5,
		"required" : false,
		"gameTime" : "2022-10-01T23:00:00Z",
		"channel": "ESPNU"
    },
    {
		"gameId" : 220,
		"awayTeam" : "TROY",
		"homeTeam" : "WKU",
		"favorite" : "WKU",
		"spread" : 4.5,
		"required" : false,
		"gameTime" : "2022-10-01T23:00:00Z",
		"channel": "ESPN+"
    },
    {
		"gameId" : 221,
		"awayTeam" : "UVA",
		"homeTeam" : "DUKE",
		"favorite" : "DUKE",
		"spread" : 2.5,
		"required" : false,
		"gameTime" : "2022-10-01T23:30:00Z",
		"channel": "ESPN3"
    },
    {
		"gameId" : 222,
		"awayTeam" : "NCST",
		"homeTeam" : "CLEM",
		"favorite" : "CLEM",
		"spread" : 6.5,
		"required" : true,
		"gameTime" : "2022-10-01T23:30:00Z",
		"channel": "ABC"
    },
    {
		"gameId" : 223,
		"awayTeam" : "UGA",
		"homeTeam" : "MIZZOU",
		"favorite" : "UGA",
		"spread" : 28.5,
		"required" : false,
		"gameTime" : "2022-10-01T23:30:00Z",
		"channel": "SECN"
    },
    {
		"gameId" : 224,
		"awayTeam" : "WVU",
		"homeTeam" : "TEXAS",
		"favorite" : "TEXAS",
		"spread" : 9.5,
		"required" : false,
		"gameTime" : "2022-10-01T23:30:00Z",
		"channel": "FS1"
    },
    {
		"gameId" : 225,
		"awayTeam" : "IND",
		"homeTeam" : "NEB",
		"favorite" : "NEB",
		"spread" : 5.5,
		"required" : false,
		"gameTime" : "2022-10-01T23:30:00Z",
		"channel": "B1G"
    },
    {
		"gameId" : 226,
		"awayTeam" : "UAB",
		"homeTeam" : "RICE",
		"favorite" : "UAB",
		"spread" : 10.5,
		"required" : false,
		"gameTime" : "2022-10-01T23:30:00Z",
		"channel": "ESPN+"
    },
    {
		"gameId" : 227,
		"awayTeam" : "SJSU",
		"homeTeam" : "WYO",
		"favorite" : "SJSU",
		"spread" : 3.5,
		"required" : false,
		"gameTime" : "2022-10-01T23:30:00Z",
		"channel": "CBSSN"
    },
    {
		"gameId" : 228,
		"awayTeam" : "GT",
		"homeTeam" : "PITT",
		"favorite" : "PITT",
		"spread" : 22.5,
		"required" : false,
		"gameTime" : "2022-10-02T00:00:00Z",
		"channel": "ACCN"
    },
    {
		"gameId" : 229,
		"awayTeam" : "FIU",
		"homeTeam" : "NMSU",
		"favorite" : "NMSU",
		"spread" : 14.5,
		"required" : false,
		"gameTime" : "2022-10-02T00:00:00Z",
		"channel": "FloSports"
    },
    {
		"gameId" : 230,
		"awayTeam" : "CU",
		"homeTeam" : "ARIZ",
		"favorite" : "ARIZ",
		"spread" : 17.5,
		"required" : false,
		"gameTime" : "2022-10-02T01:30:00Z",
		"channel": "PACN"
    },
    {
		"gameId" : 231,
		"awayTeam" : "ASU",
		"homeTeam" : "USC",
		"favorite" : "USC",
		"spread" : 26.5,
		"required" : false,
		"gameTime" : "2022-10-02T02:30:00Z",
		"channel": "ESPN"
    },
    {
		"gameId" : 232,
		"awayTeam" : "STAN",
		"homeTeam" : "ORE",
		"favorite" : "ORE",
		"spread" : 16.5,
		"required" : false,
		"gameTime" : "2022-10-02T03:00:00Z",
		"channel": "FS1"
    }
  ]
}